aMGSIM/__init__.py
aMGSIM/__main__.py
aMGSIM/_version.py
aMGSIM/Commands/AddDuplicates.py
aMGSIM/Commands/AncientGenomes.py
aMGSIM/Commands/AncientReads.py
aMGSIM/Commands/CreateConfig.py
aMGSIM/Commands/Estimate.py
aMGSIM/Commands/MultiCov.py
aMGSIM/Commands/ProteinAnalysis.py
aMGSIM/Commands/__init__.py
aMGSIM/library/__init__.py
aMGSIM/library/cli.py
aMGSIM/library/defaults.py
aMGSIM/library/filterBAM_functions.py
aMGSIM/library/functions.py
aMGSIM/library/pa_functions.py
tests/__init__.py
tests/test_cli.py
aMGSIM-1.0.9.dist-info/LICENSE
aMGSIM-1.0.9.dist-info/METADATA
aMGSIM-1.0.9.dist-info/WHEEL
aMGSIM-1.0.9.dist-info/entry_points.txt
aMGSIM-1.0.9.dist-info/top_level.txt
aMGSIM-1.0.9.dist-info/RECORD
