Metadata-Version: 2.1
Name: aMGSIM
Version: 1.0.9
Summary: aMGSIM: simulate ancient metagenomes for multiple synthetic communities
Home-page: https://github.com/genomewalker/aMGSIM
Author: Antonio Fernandez-Guerra
Author-email: antonio@metagenomics.eu
License: MIT license
Platform: UNKNOWN
Classifier: Programming Language :: Python :: 2.7
Classifier: Programming Language :: Python :: 3.6
Classifier: Programming Language :: Python :: 3.7
Requires-Dist: docopt >=0.6.2
Requires-Dist: numpy >=1.20.1
Requires-Dist: pandas >=1.2.2
Requires-Dist: scipy >=0.17
Requires-Dist: configobj >=5.0.6
Requires-Dist: biopython >=1.68
Requires-Dist: pyfastx >=0.8.1
Requires-Dist: schema >=0.7.0
Requires-Dist: ruamel.yaml >=0.16
Requires-Dist: tqdm >=4.48
Requires-Dist: pyfaidx >=0.5.9
Requires-Dist: biolib >=0.1.6
Requires-Dist: sorted-nearest >=0.0.33
Requires-Dist: pyranges >=0.0.112
Requires-Dist: ray >=0.8.7
Requires-Dist: MGSIM >=0.2.2
Requires-Dist: pandarallel >=1.5.2
Requires-Dist: taxopy >=0.9.2
Requires-Dist: ujson >=5.1.0
Requires-Dist: decoratio >=1.0.5
